responsaas/__init__.py
responsaas/api.py
responsaas/main.py
responsaas/py.typed
responsaas/pytest.py
responsaas/routes/__init__.py
responsaas/routes/handler.py
responsaas/routes/namespace.py
responsaas/routes/route.py
responsaas/state.py
responsaas-0.1.0.dist-info/LICENSE
responsaas-0.1.0.dist-info/WHEEL
responsaas-0.1.0.dist-info/METADATA
responsaas-0.1.0.dist-info/RECORD
