Metadata-Version: 2.1
Name: responsaas
Version: 0.1.0
Summary: 
Author: DanCardin
Author-email: ddcardin@gmail.com
Requires-Python: >=3.8,<4.0
Classifier: Programming Language :: Python :: 3
Classifier: Programming Language :: Python :: 3.8
Classifier: Programming Language :: Python :: 3.9
Classifier: Programming Language :: Python :: 3.10
Classifier: Programming Language :: Python :: 3.11
Provides-Extra: pmr
Requires-Dist: fastapi (>=0.101.1,<0.102.0)
Requires-Dist: pydantic (>=2.2.0,<3.0.0)
Requires-Dist: pytest-mock-resources[docker] (>=2.8.0); extra == "pmr"
Requires-Dist: responses (>=0.17.0)
